yatank_OnlineReport/__init__.py
yatank_OnlineReport/cache.py
yatank_OnlineReport/decode.py
yatank_OnlineReport/plugin.py
yatank_OnlineReport/server.py
yatank_OnlineReport/static/favicon.ico
yatank_OnlineReport/static/css/bootstrap-theme.css
yatank_OnlineReport/static/css/bootstrap-theme.css.map
yatank_OnlineReport/static/css/bootstrap-theme.min.css
yatank_OnlineReport/static/css/bootstrap.css
yatank_OnlineReport/static/css/bootstrap.css.map
yatank_OnlineReport/static/css/bootstrap.min.css
yatank_OnlineReport/static/css/custom.css
yatank_OnlineReport/static/css/rickshaw.css
yatank_OnlineReport/static/fonts/glyphicons-halflings-regular.eot
yatank_OnlineReport/static/fonts/glyphicons-halflings-regular.svg
yatank_OnlineReport/static/fonts/glyphicons-halflings-regular.ttf
yatank_OnlineReport/static/fonts/glyphicons-halflings-regular.woff
yatank_OnlineReport/static/js/angular-rickshaw.coffee
yatank_OnlineReport/static/js/angular-rickshaw.js
yatank_OnlineReport/static/js/ws.coffee
yatank_OnlineReport/static/js/ws.js
yatank_OnlineReport/static/js/vendor/angular.min.js
yatank_OnlineReport/static/js/vendor/bootstrap.min.js
yatank_OnlineReport/static/js/vendor/cubism.min.js
yatank_OnlineReport/static/js/vendor/d3.min.js
yatank_OnlineReport/static/js/vendor/jquery.min.js
yatank_OnlineReport/static/js/vendor/rickshaw.min.js
yatank_OnlineReport/static/js/vendor/socket.io.min.js
yatank_OnlineReport/templates/brief.jade
yatank_OnlineReport/templates/index.jade
yatank_OnlineReport/templates/monitoring.jade
yatank_OnlineReport/templates/offline.jade
yatank_online-0.0.8.dist-info/DESCRIPTION.rst
yatank_online-0.0.8.dist-info/METADATA
yatank_online-0.0.8.dist-info/RECORD
yatank_online-0.0.8.dist-info/WHEEL
yatank_online-0.0.8.dist-info/metadata.json
yatank_online-0.0.8.dist-info/top_level.txt
