Metadata-Version: 2.0
Name: yatank-online
Version: 0.0.8
Summary: Yandex.Tank OnlineReport plugin
Home-page: https://github.com/yandex-load/yatank-online/
Author: Alexey Lavrenuke
Author-email: direvius@gmail.com
License: UNKNOWN
Platform: UNKNOWN
Requires-Dist: pyjade (>=4.0.0)
Requires-Dist: tornadio2
Requires-Dist: tornado
